poetflow/__init__.py
poetflow/application.py
poetflow/commands/base.py
poetflow/commands/test.py
poetflow/commands/version.py
poetflow/core/cache.py
poetflow/core/changelog.py
poetflow/core/ci.py
poetflow/core/config.py
poetflow/core/dependencies.py
poetflow/core/exceptions.py
poetflow/core/hooks.py
poetflow/core/logging.py
poetflow/core/monorepo.py
poetflow/core/versioning.py
poetflow/plugins/__init__.py
poetflow/plugins/base.py
poetflow/plugins/dependency.py
poetflow/plugins/lock.py
poetflow/plugins/path.py
poetflow/plugins/path_rewriter.py
poetflow/plugins/plugin.py
poetflow/plugins/registry.py
poetflow/plugins/venv.py
poetflow/plugins/venv_modifier.py
poetflow/types/__init__.py
poetflow/types/config.py
poetflow/types/discovery.py
poetflow/types/monorepo.py
poetflow/types/poetry.py
poetflow/types/poetry_app.py
poetflow/types/poetry_commands.py
poetflow/types/stubs/poetry/config/config.pyi
poetflow/types/stubs/poetry/console/application.pyi
poetflow/types/stubs/poetry/console/command.pyi
poetflow/types/stubs/poetry/console/commands/__init__.pyi
poetflow/types/stubs/poetry/console/commands/add.pyi
poetflow/types/stubs/poetry/console/commands/base.pyi
poetflow/types/stubs/poetry/console/commands/build.pyi
poetflow/types/stubs/poetry/console/commands/command.pyi
poetflow/types/stubs/poetry/console/commands/env_command.pyi
poetflow/types/stubs/poetry/console/commands/install.pyi
poetflow/types/stubs/poetry/console/commands/installer_command.pyi
poetflow/types/stubs/poetry/console/commands/lock.pyi
poetflow/types/stubs/poetry/console/commands/remove.pyi
poetflow/types/stubs/poetry/console/commands/update.pyi
poetflow/types/stubs/poetry/factory.pyi
poetflow/types/stubs/poetry/installation/installer.pyi
poetflow/types/stubs/poetry/packages/__init__.pyi
poetflow/types/stubs/poetry/packages.pyi
poetflow/types/stubs/poetry/poetry.pyi
poetflow/types/stubs/poetry/repositories/__init__.pyi
poetflow/types/stubs/poetry/utils/env.pyi
poetflow/types/stubs/tomlkit.pyi
poetflow-0.1.0.dist-info/LICENSE
poetflow-0.1.0.dist-info/METADATA
poetflow-0.1.0.dist-info/WHEEL
poetflow-0.1.0.dist-info/entry_points.txt
poetflow-0.1.0.dist-info/RECORD
