Metadata-Version: 2.1
Name: poetflow
Version: 0.1.0
Summary: Poetry plugin for monorepo management
Author: Felipe Pimentel
Author-email: felipe@pimentel.dev
Requires-Python: >=3.10,<4.0
Classifier: Programming Language :: Python :: 3
Classifier: Programming Language :: Python :: 3.10
Classifier: Programming Language :: Python :: 3.11
Classifier: Programming Language :: Python :: 3.12
Classifier: Programming Language :: Python :: 3.13
Requires-Dist: poetry (>=1.7.0,<2.0.0)
